drf_keycloak/__init__.py
drf_keycloak/api.py
drf_keycloak/authentication.py
drf_keycloak/exceptions.py
drf_keycloak/middleware.py
drf_keycloak/permissions.py
drf_keycloak/schema.py
drf_keycloak/settings.py
drf_keycloak/token.py
drf_keycloak-1.0.3.dist-info/licenses/LICENSE.txt
drf_keycloak-1.0.3.dist-info/METADATA
drf_keycloak-1.0.3.dist-info/WHEEL
drf_keycloak-1.0.3.dist-info/top_level.txt
drf_keycloak-1.0.3.dist-info/RECORD
