Metadata-Version: 2.4
Name: drf-keycloak
Version: 1.0.3
Summary: Keycloak authentication plugin for Django REST Framework
Author-email: Sascha Rau <ideal3000developer@gmail.com>
License: MIT
Project-URL: Homepage, https://github.com/sascharau/djangorestframework-keycloak
Classifier: Development Status :: 4 - Beta
Classifier: Environment :: Web Environment
Classifier: Framework :: Django
Classifier: Framework :: Django :: 3.2
Classifier: Framework :: Django :: 4.0
Classifier: Framework :: Django :: 4.1
Classifier: Framework :: Django :: 4.2
Classifier: Framework :: Django :: 5.0
Classifier: Framework :: Django :: 5.1
Classifier: Intended Audience :: Developers
Classifier: Operating System :: OS Independent
Classifier: Programming Language :: Python
Classifier: Programming Language :: Python :: 3
Classifier: Programming Language :: Python :: 3 :: Only
Classifier: Programming Language :: Python :: 3.12
Classifier: Programming Language :: Python :: 3.13
Classifier: Topic :: Internet :: WWW/HTTP
Requires-Python: >=3.7
License-File: LICENSE.txt
Requires-Dist: requests>=2.26.0
Requires-Dist: django>=3.2
Requires-Dist: djangorestframework>=3.10
Requires-Dist: pyjwt<3,>=2
Requires-Dist: cryptography>=3.3.1
Provides-Extra: test
Requires-Dist: pytest; extra == "test"
Requires-Dist: pytest-cov; extra == "test"
Requires-Dist: pytest-django; extra == "test"
Requires-Dist: drf-spectacular; extra == "test"
Requires-Dist: tox; extra == "test"
Provides-Extra: lint
Requires-Dist: ruff; extra == "lint"
Requires-Dist: pre-commit; extra == "lint"
Provides-Extra: doc
Requires-Dist: Sphinx<2,>=1.6.5; extra == "doc"
Requires-Dist: sphinx_rtd_theme>=0.1.9; extra == "doc"
Provides-Extra: dev
Requires-Dist: pytest-watch; extra == "dev"
Requires-Dist: wheel; extra == "dev"
Requires-Dist: twine; extra == "dev"
Requires-Dist: ipython; extra == "dev"
Requires-Dist: pytest; extra == "dev"
Requires-Dist: pytest-cov; extra == "dev"
Requires-Dist: pytest-django; extra == "dev"
Requires-Dist: drf-spectacular; extra == "dev"
Requires-Dist: tox; extra == "dev"
Requires-Dist: ruff; extra == "dev"
Requires-Dist: pre-commit; extra == "dev"
Requires-Dist: Sphinx<2,>=1.6.5; extra == "dev"
Requires-Dist: sphinx_rtd_theme>=0.1.9; extra == "dev"
Requires-Dist: python-jose==3.3.0; extra == "dev"
Provides-Extra: python-jose
Requires-Dist: python-jose==3.3.0; extra == "python-jose"
Dynamic: license-file
